management/__init__.py
migrations/__init__.py
django_maker_test-1.0.dist-info/METADATA
django_maker_test-1.0.dist-info/WHEEL
django_maker_test-1.0.dist-info/top_level.txt
django_maker_test-1.0.dist-info/RECORD
