Metadata-Version: 2.1
Name: django-maker-test
Version: 1.0
Requires-Dist: Django
Requires-Dist: djangorestframework
